{
	"animations": [
		{
			"loop": false,
			"offsets": [
				1,
				0
			],
			"anim": "idle",
			"fps": 24,
			"name": "idle",
			"indices": []
		},
		{
			"loop": false,
			"offsets": [
				10,
				-1
			],
			"anim": "singLEFT",
			"fps": 24,
			"name": "left",
			"indices": []
		},
		{
			"loop": false,
			"offsets": [
				5,
				6
			],
			"anim": "singDOWN",
			"fps": 24,
			"name": "down",
			"indices": []
		},
		{
			"loop": false,
			"offsets": [
				7,
				47
			],
			"anim": "singUP",
			"fps": 24,
			"name": "up",
			"indices": []
		},
		{
			"loop": false,
			"offsets": [
				5,
				-2
			],
			"anim": "singRIGHT",
			"fps": 24,
			"name": "right",
			"indices": []
		}
	],
	"no_antialiasing": false,
	"image": "characters/badguy_assets",
	"position": [
		0,
		-120
	],
	"healthicon": "badguy",
	"flip_x": false,
	"healthbar_colors": [
		161,
		33,
		252
	],
	"camera_position": [
		-30,
		40
	],
	"sing_duration": 6.1,
	"scale": 0.8
}